{"time":24594,"apiVersion":"v1","queryOptions":{"metadata":true,"limit":-1,"skip":-1,"count":false},"response":[{"time":0,"dbTime":4,"numResults":1,"numTotalResults":1,"resultType":"uk.ac.ebi.eva.lib.models.VariantStudy","result":[{"name":"Refining the clinical context for genetic testing of SLC2A1 in patients with childhood and adolescent epilepsies","id":"PRJEB58559","description":"We aimed to investigate the presence of SLC2A1 variants in a large cohort unrelated probands with childhood and adolescence epilepsies","taxonomyId":[9606],"speciesCommonName":"Human","speciesScientificName":"Homo sapiens","sourceType":"Germline","center":"UNICAMP","material":"DNA","scope":"multi-isolate","type":"CONTROL","experimentType":"Exome Sequencing, Genotyping By Sequencing","experimentTypeAbbreviation":"ES, GBS","assembly":"-","assemblyAccession":"GCA_000001405.28","platform":"-","url":"-","publications":["-"],"numVariants":0,"numSamples":94,"browsable":true,"typeName":"Control Set"}]}]}