{"time":12974,"apiVersion":"v1","queryOptions":{"metadata":true,"limit":-1,"skip":-1,"count":false},"response":[{"time":0,"dbTime":2,"numResults":1,"numTotalResults":1,"resultType":"uk.ac.ebi.eva.lib.models.VariantStudy","result":[{"name":"Qatar variation catalogue","id":"PRJEB51505","description":"Ancestry-related distribution of Runs of homozygosity and functional variants in Qatari population","taxonomyId":[9606],"speciesCommonName":"Human","speciesScientificName":"Homo sapiens","sourceType":"Germline","center":"Institute for Maternal and Child Health, IRCCS \"Burlo Garofolo\"","material":"DNA","scope":"multi-isolate","type":"CONTROL","experimentType":"Genotyping By Array","experimentTypeAbbreviation":"Array","assembly":"-","assemblyAccession":"GCA_000001405.14","platform":"-","url":"-","publications":["-"],"numVariants":0,"numSamples":186,"browsable":true,"typeName":"Control Set"}]}]}